{"doing":[{"codename":"signboard","type":"story"},{"type":"drawing","codename":"veil"}],"done":[{"type":"painting","codename":"glanced"},{"codename":"reason","type":"drawing"},{"codename":"alike","type":"drawing"},{"type":"drawing","codename":"weary"}],"updated":"2021-06-20T15:43:24Z","todo":[{"codename":"throne","type":"drawing"},{"codename":"tendency","type":"story"},{"codename":"spill","type":"painting"},{"codename":"thoughtful","type":"painting"},{"codename":"resolute","type":"drawing"},{"codename":"encouraging","type":"story"}]}